reloadly_core/core/constant/ServiceURLs.py
reloadly_core/core/dto/APIError.py
reloadly_core/core/dto/response/Page.py
reloadly_core/core/enums/Environment.py
reloadly_core/core/enums/Service.py
reloadly_core/core/exception/APIException.py
reloadly_core/core/exception/OAuthException.py
reloadly_core/core/exception/RateLimitException.py
reloadly_core/core/exception/ReloadlyException.py
reloadly_core/core/internal/Filter/BaseFilter.py
reloadly_core/core/internal/Filter/OperatorFilter.py
reloadly_core/core/internal/Filter/QueryFilter.py
reloadly_core/core/internal/Filter/TransactionHistoryFilter.py
reloadly_core/core/internal/adapter/JackSonDateDeserializer.py
reloadly_core/core/internal/adapter/UnixEpochDateTypeAdapter.py
reloadly_core/core/internal/client/BaseOperation.py
reloadly_core/core/internal/constant/Auth.py
reloadly_core/core/internal/constant/GrantType.py
reloadly_core/core/internal/constant/HttpHeader.py
reloadly_core/core/internal/constant/MediaType.py
reloadly_core/core/internal/dto/request/BaseRequest.py
reloadly_core/core/internal/dto/request/CustomRequest.py
reloadly_core/core/internal/dto/request/CustomizableRequest.py
reloadly_core/core/internal/dto/request/interfaces/Request.py
reloadly_core/core/internal/enums/Version.py
reloadly_core/core/internal/interceptor/TelemetryInterceptor.py
reloadly_core/core/internal/net/API.py
reloadly_core/core/internal/net/ServiceAPI.py
reloadly_core/core/internal/net/Telemetry-python.py
reloadly_core/core/internal/net/Telemetry.py
reloadly_core/core/internal/util/Asserter.py
reloadly_core/core/internal/util/ExceptionUtil.py
reloadly_core/core/internal/util/TelemetryUtil.py
reloadly_core/core/net/HttpOptions.py
reloadly_core/core/net/ProxyOptions.py
reloadly_core-1.1.1.dist-info/METADATA
reloadly_core-1.1.1.dist-info/WHEEL
reloadly_core-1.1.1.dist-info/top_level.txt
reloadly_core-1.1.1.dist-info/RECORD
